.gitignore
LICENSE
MANIFEST.in
Makefile
README.md
README.rst
pypi-push.sh
requirements-test.txt
setup.py
tests.sh
swift_commander/__init__.py
swift_commander/swbundler.py
swift_commander/swc
swift_commander/swfoldersize.py
swift_commander/swhashcomp.py
swift_commander/swpget.py
swift_commander/swrm.py
swift_commander/swsearch.py
swift_commander/swsymlinks.py
swift_commander.egg-info/PKG-INFO
swift_commander.egg-info/SOURCES.txt
swift_commander.egg-info/dependency_links.txt
swift_commander.egg-info/entry_points.txt
swift_commander.egg-info/requires.txt
swift_commander.egg-info/top_level.txt